LICENSE
README.md
setup.cfg
setup.py
hinpy/__init__.py
hinpy/general.py
hinpy.egg-info/PKG-INFO
hinpy.egg-info/SOURCES.txt
hinpy.egg-info/dependency_links.txt
hinpy.egg-info/requires.txt
hinpy.egg-info/top_level.txt
hinpy/classes/__init__.py
hinpy/classes/hin_class.py
hinpy/classes/hin_functions.py
hinpy/classes/hin_graphics.py
hinpy/classes/link_group_class.py
hinpy/classes/link_group_functions.py
hinpy/classes/object_group_class.py
hinpy/datasets/__init__.py
hinpy/datasets/generators.py
hinpy/diversity/__init__.py
hinpy/diversity/classic_measures.py
hinpy/diversity/diversities_measures.py
hinpy/diversity/other_measures.py
hinpy/diversity/truediversity.py
hinpy/diversity/utils.py
hinpy/generators/__init__.py
hinpy/generators/random_graphs.py
hinpy/rs/__init__.py
hinpy/rs/content_based.py
hinpy/rs/hin_rs.py
hinpy/rs/implicit_utility.py
hinpy/rs/pure_popularity.py
hinpy/rs/random_rs.py
hinpy/rs/surprise_based.py