Metadata-Version: 1.1
Name: hinpy
Version: 0.1.11
Summary: A python framework for Heterogeneous Information Networks.
Home-page: https://github.com/pedroramaciotti/HINPy
Author: Pedro Ramaciotti Morales
Author-email: pedro.ramaciotti@gmail.com
License: UNKNOWN
Download-URL: https://github.com/pedroramaciotti/HINPy/archive/0.1.11.tar.gz
Keywords: Heterogeneous Information Networks,Recommender Systems,Diversity,Echo Chamber,Filter Bubble
Platform: UNKNOWN
